{
  "as_of": "2026-03-06T21:51:16.168954+00:00",
  "method": "free-float market cap",
  "constituents": [
    {
      "symbol": "BTC",
      "weight": 0.3,
      "market_cap": 1365215722235.0
    },
    {
      "symbol": "ETH",
      "weight": 0.22,
      "market_cap": 238862794916.0
    },
    {
      "symbol": "XRP",
      "weight": 0.06,
      "market_cap": 83310299514.0
    },
    {
      "symbol": "BNB",
      "weight": 0.06,
      "market_cap": 85807415486.0
    },
    {
      "symbol": "SOL",
      "weight": 0.06,
      "market_cap": 48233248306.0
    },
    {
      "symbol": "TRX",
      "weight": 0.06,
      "market_cap": 26975678646.0
    },
    {
      "symbol": "DOGE",
      "weight": 0.06,
      "market_cap": 13951328454.0
    },
    {
      "symbol": "BCH",
      "weight": 0.06,
      "market_cap": 9000117847.0
    },
    {
      "symbol": "ADA",
      "weight": 0.06,
      "market_cap": 9534854966.0
    },
    {
      "symbol": "LEO",
      "weight": 0.06,
      "market_cap": 8333864948.0
    }
  ]
}