{
  "as_of": "2026-03-18T20:29:05.484760+00:00",
  "method": "free-float market cap",
  "constituents": [
    {
      "symbol": "BTC",
      "weight": 0.3,
      "market_cap": 1418180926809.0
    },
    {
      "symbol": "ETH",
      "weight": 0.22,
      "market_cap": 262429775081.0
    },
    {
      "symbol": "XRP",
      "weight": 0.06,
      "market_cap": 88893234869.0
    },
    {
      "symbol": "BNB",
      "weight": 0.06,
      "market_cap": 88313477878.0
    },
    {
      "symbol": "SOL",
      "weight": 0.06,
      "market_cap": 51109122767.0
    },
    {
      "symbol": "TRX",
      "weight": 0.06,
      "market_cap": 28732326975.0
    },
    {
      "symbol": "DOGE",
      "weight": 0.06,
      "market_cap": 14499415991.0
    },
    {
      "symbol": "BCH",
      "weight": 0.06,
      "market_cap": 9064130295.0
    },
    {
      "symbol": "ADA",
      "weight": 0.06,
      "market_cap": 10007267374.0
    },
    {
      "symbol": "LEO",
      "weight": 0.06,
      "market_cap": 8332871471.0
    }
  ]
}