{
  "as_of": "2026-03-15T12:37:24.495631+00:00",
  "method": "free-float market cap",
  "constituents": [
    {
      "symbol": "BTC",
      "weight": 0.3,
      "market_cap": 1434518671039.0
    },
    {
      "symbol": "ETH",
      "weight": 0.22,
      "market_cap": 255475804034.0
    },
    {
      "symbol": "XRP",
      "weight": 0.06,
      "market_cap": 86794815482.0
    },
    {
      "symbol": "BNB",
      "weight": 0.06,
      "market_cap": 90152377893.0
    },
    {
      "symbol": "SOL",
      "weight": 0.06,
      "market_cap": 50512941509.0
    },
    {
      "symbol": "TRX",
      "weight": 0.06,
      "market_cap": 28176465115.0
    },
    {
      "symbol": "DOGE",
      "weight": 0.06,
      "market_cap": 14776875208.0
    },
    {
      "symbol": "BCH",
      "weight": 0.06,
      "market_cap": 9342880231.0
    },
    {
      "symbol": "ADA",
      "weight": 0.06,
      "market_cap": 9783627813.0
    },
    {
      "symbol": "LEO",
      "weight": 0.06,
      "market_cap": 8358934126.0
    }
  ]
}