{
  "as_of": "2026-03-02T06:10:39.115568+00:00",
  "method": "free-float market cap",
  "constituents": [
    {
      "symbol": "BTC",
      "weight": 0.3,
      "market_cap": 1334147428453.0
    },
    {
      "symbol": "ETH",
      "weight": 0.22,
      "market_cap": 237898038605.0
    },
    {
      "symbol": "XRP",
      "weight": 0.06,
      "market_cap": 83339450011.0
    },
    {
      "symbol": "BNB",
      "weight": 0.06,
      "market_cap": 85020030491.0
    },
    {
      "symbol": "SOL",
      "weight": 0.06,
      "market_cap": 48038542910.0
    },
    {
      "symbol": "TRX",
      "weight": 0.06,
      "market_cap": 26629029282.0
    },
    {
      "symbol": "DOGE",
      "weight": 0.06,
      "market_cap": 15736805455.0
    },
    {
      "symbol": "BCH",
      "weight": 0.06,
      "market_cap": 9050370296.0
    },
    {
      "symbol": "ADA",
      "weight": 0.06,
      "market_cap": 10145971890.0
    },
    {
      "symbol": "LEO",
      "weight": 0.06,
      "market_cap": 8405171224.0
    }
  ]
}